c2py/__init__.py
c2py-0.0.1.dist-info/LICENSE
c2py-0.0.1.dist-info/METADATA
c2py-0.0.1.dist-info/WHEEL
c2py-0.0.1.dist-info/top_level.txt
c2py-0.0.1.dist-info/RECORD
