Metadata-Version: 2.1
Name: c2py
Version: 0.0.1
Summary: Create python wrappers that call c functions (without the headaches).
Home-page: https://github.com/i2mint/c2py
License: mit
Platform: any
